SRP/SRP.py
SRP/SRP_files.py
SRP/__init__.py
SRP/flycheck_SRP.py
pysrp-1.1.0.dist-info/LICENSE
pysrp-1.1.0.dist-info/METADATA
pysrp-1.1.0.dist-info/WHEEL
pysrp-1.1.0.dist-info/top_level.txt
pysrp-1.1.0.dist-info/RECORD
