Metadata-Version: 2.1
Name: pysrp
Version: 1.1.0
Summary: Run stable random projections.
Home-page: http://github.com/bmschmidt/SRP
Author: Benjamin Schmidt
Author-email: bmschmidt@gmail.com
License: MIT
Platform: UNKNOWN
Classifier: Development Status :: 4 - Beta
Classifier: Intended Audience :: Education
Classifier: Natural Language :: English
Classifier: License :: OSI Approved :: MIT License
Classifier: Operating System :: Unix
Classifier: Programming Language :: Python :: 3.6
Classifier: Programming Language :: Python :: 3.7
Classifier: Programming Language :: Python :: 3.8
Classifier: Programming Language :: Python :: 3.9
Classifier: Topic :: Text Processing :: Indexing
Classifier: Topic :: Text Processing :: Linguistic
License-File: LICENSE
Requires-Dist: numpy
Requires-Dist: regex
Requires-Dist: sqlitedict
